LICENSE
kiwis/__init__.py
kiwis/__main__.py
kiwis/config.py
kiwis/exceptions.py
kiwis/kiwis.py
kiwis/utils.py
kiwis-0.1.0b1.dist-info/entry_points.txt
kiwis-0.1.0b1.dist-info/LICENSE
kiwis-0.1.0b1.dist-info/WHEEL
kiwis-0.1.0b1.dist-info/METADATA
kiwis-0.1.0b1.dist-info/RECORD
